pyshare/__init__.py
pyshare/config.py
pyshare/main.py
pyshare/network_utils.py
pyshare/receiver.py
pyshare/sender.py
pyshare/ui.py
pyshare/utils.py
pyshareit-1.11.0.dist-info/licenses/LICENSE
pyshareit-1.11.0.dist-info/METADATA
pyshareit-1.11.0.dist-info/WHEEL
pyshareit-1.11.0.dist-info/entry_points.txt
pyshareit-1.11.0.dist-info/top_level.txt
pyshareit-1.11.0.dist-info/RECORD
