Metadata-Version: 2.4
Name: pyshareit
Version: 1.11.0
Summary: A fast, peer-to-peer file sharing tool with a simple terminal interface.
Author-email: RAGUNATH R <ragunathravi73@gmail.com>
License: GPL-3.0-or-later
Project-URL: Homepage, https://github.com/ragu-123/pyshare-cli
Project-URL: Issues, https://github.com/ragu-123/pyshare-cli/issues
Keywords: file-transfer,p2p,networking,tui,quic,fast-transfer
Classifier: Development Status :: 4 - Beta
Classifier: Environment :: Console
Classifier: License :: OSI Approved :: GNU General Public License v3 or later (GPLv3+)
Classifier: Programming Language :: Python :: 3.9
Classifier: Programming Language :: Python :: 3.10
Classifier: Programming Language :: Python :: 3.11
Classifier: Topic :: Communications :: File Sharing
License-File: LICENSE
Requires-Dist: tqdm
Requires-Dist: colorama
Requires-Dist: cryptography
Requires-Dist: pyperclip
Requires-Dist: pyreadline3; sys_platform == "win32"
Dynamic: license-file
